_oldfiles/src/gray2bin.sv
`timescale 1ns / 1ps
`default_nettype none

module gray2bin
    #(
        parameter BINARY_WIDTH = 8
    )
    (
        output reg [BINARY_WIDTH - 1: 0] binary,
        input wire [BINARY_WIDTH - 1: 0] gray
    );

    integer i;

    always_comb begin
        for(i = 0; i < BINARY_WIDTH; i++) begin
            binary[i] = ^(gray >> i);
        end
    end

endmodule

_oldfiles/src/bin2gray.sv
`timescale 1ns / 1ps
`default_nettype none

module bin2gray
    #(
        parameter BINARY_WIDTH = 8
    )
    (
        input wire [BINARY_WIDTH - 1: 0] binary,
        output reg [BINARY_WIDTH - 1: 0] gray
    );

    always_comb begin 
        gray = binary >> 1 ^ binary;
    end

endmodule

_oldfiles/src/dual_port_fifo.sv
`timescale 1ns / 1ps
`default_nettype none

module dual_port_fifo
    #(
        parameter DATA_WIDTH = 16,
        parameter FIFO_DEPTH = 32
    )(
        input wire wr_clk,
        input wire wr_en,
        input wire [DATA_WIDTH - 1: 0] wr_data,
        output reg full,

        input wire rd_clk,
        input wire rd_en,
        output reg [DATA_WIDTH - 1: 0] rd_data,
        output wire empty,

        input wire reset
    );

    localparam POINTER_WIDTH = $clog2(FIFO_DEPTH);

    logic [DATA_WIDTH - 1: 0] fifo_data [FIFO_DEPTH - 1: 0];

    //READ CLOCK DOMAIN
    logic [POINTER_WIDTH:0] rd_pointer_binary;
    logic [POINTER_WIDTH:0] rd_pointer_gray;   
    logic [POINTER_WIDTH:0] rd_pointer_gray_incremented;   
    logic [POINTER_WIDTH:0] rdcdc_wr_pointer_gray;

    gray2bin #(.BINARY_WIDTH(POINTER_WIDTH + 1))
        rd_side_g2b(.gray(rd_pointer_gray), .binary(rd_pointer_binary));
    
    bin2gray #(.BINARY_WIDTH(POINTER_WIDTH + 1))
        rd_side_b2g(.gray(rd_pointer_gray_incremented), .binary(rd_pointer_binary + 1'b1));
    
        
    assign empty = rdcdc_wr_pointer_gray == rd_pointer_gray;

    always @(*) begin
        rd_data <= fifo_data[rd_pointer_binary[POINTER_WIDTH-1:0]];
    end

    always @(posedge rd_clk) begin
        //CDC of wr pointer
        rdcdc_wr_pointer_gray <= wr_pointer_gray;
        if(reset) begin
            rd_pointer_gray <= 0;
        end else begin
            if(rd_en & ~empty) begin
                rd_pointer_gray = rd_pointer_gray_incremented;
            end
        end
    end

    ///WRITE CLOCK DOMAIN
    logic [POINTER_WIDTH:0] wr_pointer_binary;
    logic [POINTER_WIDTH:0] wr_pointer_gray;   
    logic [POINTER_WIDTH:0] wr_pointer_gray_incremented;   
    logic [POINTER_WIDTH:0] wrcdc_rd_pointer_gray;
    logic [POINTER_WIDTH:0] wrcdc_rd_pointer_binary;
    
    gray2bin #(.BINARY_WIDTH(POINTER_WIDTH + 1))
        wr_side_g2b(.gray(wr_pointer_gray), .binary(wr_pointer_binary));
    
    bin2gray #(.BINARY_WIDTH(POINTER_WIDTH + 1))
        wr_side_b2g(.gray(wr_pointer_gray_incremented), .binary(wr_pointer_binary + 1'b1));

    gray2bin #(.BINARY_WIDTH(POINTER_WIDTH + 1))
        wr_side_pointer_g2b(.gray(wrcdc_rd_pointer_gray), .binary(wrcdc_rd_pointer_binary));
    
    assign full = wrcdc_rd_pointer_binary == {~wr_pointer_binary[POINTER_WIDTH], wr_pointer_binary[POINTER_WIDTH - 1:0]};

    always @(posedge wr_clk) begin
        wrcdc_rd_pointer_gray <= rd_pointer_gray;
        if(reset) begin
            wr_pointer_gray <= 0;
        end else begin
            if(wr_en & ~full) begin
                fifo_data[wr_pointer_binary[POINTER_WIDTH-1:0]] <= wr_data;
                wr_pointer_gray <= wr_pointer_gray_incremented;
            end
        end
    end
endmodule

_oldfiles/src_test/fifo/dual_port_fifo.vcd
$date
	Tue Aug 24 16:51:46 2021
$end
$version
	Icarus Verilog
$end
$timescale
	1ps
$end
$scope module dual_port_fifo $end
$var wire 1 ! rd_clk $end
$var wire 1 " rd_en $end
$var wire 1 # reset $end
$var wire 1 $ wr_clk $end
$var wire 16 % wr_data [15:0] $end
$var wire 1 & wr_en $end
$var wire 6 ' wrcdc_rd_pointer_binary [5:0] $end
$var wire 6 ( wr_pointer_gray_incremented [5:0] $end
$var wire 6 ) wr_pointer_binary [5:0] $end
$var wire 6 * rd_pointer_gray_incremented [5:0] $end
$var wire 6 + rd_pointer_binary [5:0] $end
$var wire 1 , full $end
$var wire 1 - empty $end
$var reg 16 . rd_data [15:0] $end
$var reg 6 / rd_pointer_gray [5:0] $end
$var reg 6 0 rdcdc_wr_pointer_gray [5:0] $end
$var reg 6 1 wr_pointer_gray [5:0] $end
$var reg 6 2 wrcdc_rd_pointer_gray [5:0] $end
$scope module rd_side_b2g $end
$var wire 6 3 binary [5:0] $end
$var reg 6 4 gray [5:0] $end
$upscope $end
$scope module rd_side_g2b $end
$var wire 6 5 gray [5:0] $end
$var reg 6 6 binary [5:0] $end
$var integer 32 7 i [31:0] $end
$upscope $end
$scope module wr_side_b2g $end
$var wire 6 8 binary [5:0] $end
$var reg 6 9 gray [5:0] $end
$upscope $end
$scope module wr_side_g2b $end
$var wire 6 : gray [5:0] $end
$var reg 6 ; binary [5:0] $end
$var integer 32 < i [31:0] $end
$upscope $end
$scope module wr_side_pointer_g2b $end
$var wire 6 = gray [5:0] $end
$var reg 6 > binary [5:0] $end
$var integer 32 ? i [31:0] $end
$upscope $end
$upscope $end
$enddefinitions $end
#0
$dumpvars
b110 ?
bx >
bx =
b110 <
b0 ;
b0 :
b1 9
b1 8
b110 7
b0 6
b0 5
b1 4
b1 3
bx 2
b0 1
bx 0
b0 /
bx .
x-
x,
b0 +
b1 *
b0 )
b1 (
bx '
0&
bz %
1$
1#
0"
1!
$end
#3500
0!
#6500
0$
#7000
1-
b0 0
1!
#10500
0!
#13000
0#
b110 7
b110 <
0,
b0 '
b0 >
b110 ?
b0 2
b0 =
1$
#14000
1!
#17500
0!
#19500
0$
#21000
1!
#24500
0!
#26000
1$
#28000
1!
#31500
0!
#32500
1&
b1110110000011010 %
0$
#35000
1!
#38500
0!
#39000
b1110110000011010 .
b11 (
b11 9
b110 7
b10 8
b1 )
b1 ;
b110 <
b1 1
b1 :
1$
#42000
0-
b1 0
1!
#45500
b1001100110010101 %
0$
0!
#49000
1!
#52000
b10 (
b10 9
b110 7
b11 8
b10 )
b10 ;
b110 <
b11 1
b11 :
1$
#52500
0!
#56000
b11 0
1!
#58500
b11110100000001 %
0$
#59500
0!
#63000
1!
#65000
b110 (
b110 9
b110 7
b100 8
b11 )
b11 ;
b110 <
b10 1
b10 :
1$
#66500
0!
#70000
b10 0
1!
#71500
b1111100100010111 %
0$
#73500
0!
#77000
1!
#78000
b111 (
b111 9
b110 7
b101 8
b100 )
b100 ;
b110 <
b110 1
b110 :
1$
#80500
0!
#84000
b110 0
1!
#84500
b110001001110010 %
0$
#87500
0!
#91000
b101 (
b101 9
b110 7
b110 8
b101 )
b101 ;
b110 <
b111 1
b111 :
1$
1!
#94500
0!
#97500
b1101101010100001 %
0$
#98000
b111 0
1!
#101500
0!
#104000
b100 (
b100 9
b110 7
b111 8
b110 )
b110 ;
b110 <
b101 1
b101 :
1$
#105000
b101 0
1!
#108500
0!
#110500
b1110110001111001 %
0$
#112000
1!
#115500
0!
#117000
b1100 (
b1100 9
b110 7
b1000 8
b111 )
b111 ;
b110 <
b100 1
b100 :
1$
#119000
b100 0
1!
#122500
0!
#123500
b1101110001011101 %
0$
#126000
1!
#129500
0!
#130000
b1101 (
b1101 9
b110 7
b1001 8
b1000 )
b1000 ;
b110 <
b1100 1
b1100 :
1$
#133000
b1100 0
1!
#136500
b10101110010001 %
0$
0!
#140000
1!
#143000
b1111 (
b1111 9
b110 7
b1010 8
b1001 )
b1001 ;
b110 <
b1101 1
b1101 :
1$
#143500
0!
#147000
b1101 0
1!
#149500
b10000000011000 %
0$
#150500
0!
#154000
1!
#156000
b1110 (
b1110 9
b110 7
b1011 8
b1010 )
b1010 ;
b110 <
b1111 1
b1111 :
1$
#157500
0!
#161000
b1111 0
1!
#162500
b100100011011100 %
0$
#164500
0!
#168000
1!
#169000
b1010 (
b1010 9
b110 7
b1100 8
b1011 )
b1011 ;
b110 <
b1110 1
b1110 :
1$
#171500
0!
#175000
b1110 0
1!
#175500
b1001101101110101 %
0$
#178500
0!
#182000
b1011 (
b1011 9
b110 7
b1101 8
b1100 )
b1100 ;
b110 <
b1010 1
b1010 :
1$
1!
#185500
0!
#188500
b110101110110001 %
0$
#189000
b1010 0
1!
#192500
0!
#195000
b1001 (
b1001 9
b110 7
b1110 8
b1101 )
b1101 ;
b110 <
b1011 1
b1011 :
1$
#196000
b1011 0
1!
#199500
0!
#201500
b1000001100001110 %
0$
#203000
1!
#206500
0!
#208000
b1000 (
b1000 9
b110 7
b1111 8
b1110 )
b1110 ;
b110 <
b1001 1
b1001 :
1$
#210000
b1001 0
1!
#213500
0!
#214500
b1011001110001001 %
0$
#217000
1!
#220500
0!
#221000
b11000 (
b11000 9
b110 7
b10000 8
b1111 )
b1111 ;
b110 <
b1000 1
b1000 :
1$
#224000
b1000 0
1!
#227500
b1010111000000101 %
0$
0!
#231000
1!
#234000
b11001 (
b11001 9
b110 7
b10001 8
b10000 )
b10000 ;
b110 <
b11000 1
b11000 :
1$
#234500
0!
#238000
b11000 0
1!
#240500
b1100101101111010 %
0$
#241500
0!
#245000
1!
#247000
b11011 (
b11011 9
b110 7
b10010 8
b10001 )
b10001 ;
b110 <
b11001 1
b11001 :
1$
#248500
0!
#252000
b11001 0
1!
#253500
b1011110100011011 %
0$
#255500
0!
#259000
1!
#260000
b11010 (
b11010 9
b110 7
b10011 8
b10010 )
b10010 ;
b110 <
b11011 1
b11011 :
1$
#262500
0!
#266000
b11011 0
1!
#266500
b10001000010010 %
0$
#269500
0!
#273000
b11110 (
b11110 9
b110 7
b10100 8
b10011 )
b10011 ;
b110 <
b11010 1
b11010 :
1$
1!
#276500
0!
#279500
b1010011001101100 %
0$
#280000
b11010 0
1!
#283500
0!
#286000
b11111 (
b11111 9
b110 7
b10101 8
b10100 )
b10100 ;
b110 <
b11110 1
b11110 :
1$
#287000
b11110 0
1!
#290500
0!
#292500
b1100000101111 %
0$
#294000
1!
#297500
0!
#299000
b11101 (
b11101 9
b110 7
b10110 8
b10101 )
b10101 ;
b110 <
b11111 1
b11111 :
1$
#301000
b11111 0
1!
#304500
0!
#305500
b1010001101101011 %
0$
#308000
1!
#311500
0!
#312000
b11100 (
b11100 9
b110 7
b10111 8
b10110 )
b10110 ;
b110 <
b11101 1
b11101 :
1$
#315000
b11101 0
1!
#318500
b100001011101001 %
0$
0!
#322000
1!
#325000
b10100 (
b10100 9
b110 7
b11000 8
b10111 )
b10111 ;
b110 <
b11100 1
b11100 :
1$
#325500
0!
#329000
b11100 0
1!
#331500
b11111111011010 %
0$
#332500
0!
#336000
1!
#338000
b10101 (
b10101 9
b110 7
b11001 8
b11000 )
b11000 ;
b110 <
b10100 1
b10100 :
1$
#339500
0!
#343000
b10100 0
1!
#344500
b110100101110100 %
0$
#346500
0!
#350000
1!
#351000
b10111 (
b10111 9
b110 7
b11010 8
b11001 )
b11001 ;
b110 <
b10101 1
b10101 :
1$
#353500
0!
#357000
b10101 0
1!
#357500
b1010000101101111 %
0$
#360500
0!
#364000
b10110 (
b10110 9
b110 7
b11011 8
b11010 )
b11010 ;
b110 <
b10111 1
b10111 :
1$
1!
#367500
0!
#370500
b111101001000000 %
0$
#371000
b10111 0
1!
#374500
0!
#377000
b10010 (
b10010 9
b110 7
b11100 8
b11011 )
b11011 ;
b110 <
b10110 1
b10110 :
1$
#378000
b10110 0
1!
#381500
0!
#383500
b110011101111111 %
0$
#385000
1!
#388500
0!
#390000
b10011 (
b10011 9
b110 7
b11101 8
b11100 )
b11100 ;
b110 <
b10010 1
b10010 :
1$
#392000
b10010 0
1!
#395500
0!
#396500
b1100110011011000 %
0$
#399000
1!
#402500
0!
#403000
b10001 (
b10001 9
b110 7
b11110 8
b11101 )
b11101 ;
b110 <
b10011 1
b10011 :
1$
#406000
b10011 0
1!
#409500
b1011110110111010 %
0$
0!
#413000
1!
#416000
b10000 (
b10000 9
b110 7
b11111 8
b11110 )
b11110 ;
b110 <
b10001 1
b10001 :
1$
#416500
0!
#420000
b10001 0
1!
#422500
b1000001100001101 %
0$
#423500
0!
#427000
1!
#429000
b110000 (
b110000 9
b110 7
b100000 8
b11111 )
b11111 ;
b110 <
b10000 1
b10000 :
1$
#430500
0!
#434000
b10000 0
1!
#435500
b101111001100 %
0$
#437500
0!
#441000
1!
#442000
1,
b110001 (
b110001 9
b110 7
b100001 8
b100000 )
b100000 ;
b110 <
b110000 1
b110000 :
1$
#444500
0!
#448000
b110000 0
1!
#448500
0&
bz %
0$
#451500
1"
0!
#455000
b110 <
0,
b1 '
b1 >
b110 ?
b1001100110010101 .
b1 2
b1 =
b11 *
b11 4
b10 3
b1 +
b1 6
b110 7
b1 /
b1 5
1$
1!
#458500
0!
#461500
0$
#462000
b11110100000001 .
b10 *
b10 4
b11 3
b10 +
b10 6
b110 7
b11 /
b11 5
1!
#465500
0!
#468000
b110 7
b110 <
0,
b10 '
b10 >
b110 ?
b11 2
b11 =
1$
#469000
b1111100100010111 .
b110 *
b110 4
b100 3
b11 +
b11 6
b110 7
b10 /
b10 5
1!
#472500
0!
#474500
0$
#476000
b110001001110010 .
b111 *
b111 4
b101 3
b100 +
b100 6
b110 7
b110 /
b110 5
1!
#479500
0!
#481000
b110 7
b110 <
0,
b100 '
b100 >
b110 ?
b110 2
b110 =
1$
#483000
b1101101010100001 .
b101 *
b101 4
b110 3
b101 +
b101 6
b110 7
b111 /
b111 5
1!
#486500
0!
#487500
0$
#490000
b1110110001111001 .
b100 *
b100 4
b111 3
b110 +
b110 6
b110 7
b101 /
b101 5
1!
#493500
0!
#494000
b110 7
b110 <
b110 '
b110 >
b110 ?
b101 2
b101 =
1$
#497000
b1101110001011101 .
b1100 *
b1100 4
b1000 3
b111 +
b111 6
b110 7
b100 /
b100 5
1!
#500500
0$
0!
#504000
b10101110010001 .
b1101 *
b1101 4
b1001 3
b1000 +
b1000 6
b110 7
b1100 /
b1100 5
1!
#507000
b110 7
b110 <
0,
b1000 '
b1000 >
b110 ?
b1100 2
b1100 =
1$
#507500
0!
#511000
b10000000011000 .
b1111 *
b1111 4
b1010 3
b1001 +
b1001 6
b110 7
b1101 /
b1101 5
1!
#513500
0$
#514500
0!
#518000
b100100011011100 .
b1110 *
b1110 4
b1011 3
b1010 +
b1010 6
b110 7
b1111 /
b1111 5
1!
#520000
b110 7
b110 <
b1010 '
b1010 >
b110 ?
b1111 2
b1111 =
1$
#521500
0!
#525000
b1001101101110101 .
b1010 *
b1010 4
b1100 3
b1011 +
b1011 6
b110 7
b1110 /
b1110 5
1!
#526500
0$
#528500
0!
#532000
b110101110110001 .
b1011 *
b1011 4
b1101 3
b1100 +
b1100 6
b110 7
b1010 /
b1010 5
1!
#533000
b110 7
b110 <
b1100 '
b1100 >
b110 ?
b1010 2
b1010 =
1$
#535500
0!
#539000
b1000001100001110 .
b1001 *
b1001 4
b1110 3
b1101 +
b1101 6
b110 7
b1011 /
b1011 5
1!
#539500
0$
#542500
0!
#546000
b110 <
b1110 '
b1110 >
b110 ?
b1011001110001001 .
b1001 2
b1001 =
b1000 *
b1000 4
b1111 3
b1110 +
b1110 6
b110 7
b1001 /
b1001 5
1$
1!
#549500
0!
#552500
0$
#553000
b1010111000000101 .
b11000 *
b11000 4
b10000 3
b1111 +
b1111 6
b110 7
b1000 /
b1000 5
1!
#556500
0!
#559000
b110 7
b110 <
b1111 '
b1111 >
b110 ?
b1000 2
b1000 =
1$
#560000
b1100101101111010 .
b11001 *
b11001 4
b10001 3
b10000 +
b10000 6
b110 7
b11000 /
b11000 5
1!
#563500
0!
#565500
0$
#567000
b1011110100011011 .
b11011 *
b11011 4
b10010 3
b10001 +
b10001 6
b110 7
b11001 /
b11001 5
1!
#570500
0!
#572000
b110 7
b110 <
b10001 '
b10001 >
b110 ?
b11001 2
b11001 =
1$
#574000
b10001000010010 .
b11010 *
b11010 4
b10011 3
b10010 +
b10010 6
b110 7
b11011 /
b11011 5
1!
#577500
0!
#578500
0$
#581000
b1010011001101100 .
b11110 *
b11110 4
b10100 3
b10011 +
b10011 6
b110 7
b11010 /
b11010 5
1!
#584500
0!
#585000
b110 7
b110 <
b10011 '
b10011 >
b110 ?
b11010 2
b11010 =
1$
#588000
b1100000101111 .
b11111 *
b11111 4
b10101 3
b10100 +
b10100 6
b110 7
b11110 /
b11110 5
1!
#591500
0$
0!
#595000
b1010001101101011 .
b11101 *
b11101 4
b10110 3
b10101 +
b10101 6
b110 7
b11111 /
b11111 5
1!
#598000
b110 7
b110 <
b10101 '
b10101 >
b110 ?
b11111 2
b11111 =
1$
#598500
0!
#602000
b100001011101001 .
b11100 *
b11100 4
b10111 3
b10110 +
b10110 6
b110 7
b11101 /
b11101 5
1!
#604500
0$
#605500
0!
#609000
b11111111011010 .
b10100 *
b10100 4
b11000 3
b10111 +
b10111 6
b110 7
b11100 /
b11100 5
1!
#611000
b110 7
b110 <
b10111 '
b10111 >
b110 ?
b11100 2
b11100 =
1$
#612500
0!
#616000
b110100101110100 .
b10101 *
b10101 4
b11001 3
b11000 +
b11000 6
b110 7
b10100 /
b10100 5
1!
#617500
0$
#619500
0!
#623000
b1010000101101111 .
b10111 *
b10111 4
b11010 3
b11001 +
b11001 6
b110 7
b10101 /
b10101 5
1!
#624000
b110 7
b110 <
b11001 '
b11001 >
b110 ?
b10101 2
b10101 =
1$
#626500
0!
#630000
b111101001000000 .
b10110 *
b10110 4
b11011 3
b11010 +
b11010 6
b110 7
b10111 /
b10111 5
1!
#630500
0$
#633500
0!
#637000
b110 <
b11011 '
b11011 >
b110 ?
b110011101111111 .
b10110 2
b10110 =
b10010 *
b10010 4
b11100 3
b11011 +
b11011 6
b110 7
b10110 /
b10110 5
1$
1!
#640500
0!
#643500
0$
#644000
b1100110011011000 .
b10011 *
b10011 4
b11101 3
b11100 +
b11100 6
b110 7
b10010 /
b10010 5
1!
#647500
0!
#650000
b110 7
b110 <
b11100 '
b11100 >
b110 ?
b10010 2
b10010 =
1$
#651000
b1011110110111010 .
b10001 *
b10001 4
b11110 3
b11101 +
b11101 6
b110 7
b10011 /
b10011 5
1!
#654500
0!
#656500
0$
#658000
b1000001100001101 .
b10000 *
b10000 4
b11111 3
b11110 +
b11110 6
b110 7
b10001 /
b10001 5
1!
#661500
0!
#663000
b110 7
b110 <
b11110 '
b11110 >
b110 ?
b10001 2
b10001 =
1$
#665000
b101111001100 .
b110000 *
b110000 4
b100000 3
b11111 +
b11111 6
b110 7
b10000 /
b10000 5
1!
#668500
0!
#669500
0$
#672000
b1110110000011010 .
b110001 *
b110001 4
b100001 3
b100000 +
b100000 6
b110 7
1-
b110000 /
b110000 5
1!
#675500
0!
#675501
b1 (
b1 9
b1 *
b1 4
b1 8
b0 )
b0 ;
b110 <
1,
b100000 '
b100000 >
b110 ?
b1 3
b0 +
b0 6
b110 7
b0 1
b0 :
b110000 2
b110000 =
0-
b0 /
b0 5
0"
1#
1$
1!
#679001
0!
#682001
0$
#682501
1-
b0 0
1!
#686001
0!
#688501
0#
b110 7
b110 <
0,
b0 '
b0 >
b110 ?
b0 2
b0 =
1$
#689501
1!
#693001
0!
#695001
0$
#696501
1!
#700001
0!
#701501
1$
#703501
1!
#707001
0!
#708001
0$
#710501
1!
#714001
0!
#714501
1$
#717501
1!
#721001
1&
b110111111010010 %
0$
0!
#724501
1!
#727501
0&
bz %
b110111111010010 .
b11 (
b11 9
b110 7
b10 8
b1 )
b1 ;
b110 <
b1 1
b1 :
1$
#728001
0!
#731501
0-
b1 0
1!
#734001
1&
b111000001110001 %
0$
#735001
0!
#738501
1!
#740501
b10 (
b10 9
b110 7
b11 8
b10 )
b10 ;
b110 <
b11 1
b11 :
1$
#742001
0!
#745501
b11 0
1!
#747001
b101111101001110 %
0$
#749001
0!
#752501
1!
#753501
0&
bz %
b110 (
b110 9
b110 7
b100 8
b11 )
b11 ;
b110 <
b10 1
b10 :
1$
#756001
1"
0!
#759501
b111000001110001 .
b10 0
b11 *
b11 4
b10 3
b1 +
b1 6
b110 7
b1 /
b1 5
1!
#760001
0$
#763001
0!
#766501
0"
b110 <
b10 '
b10 >
b110 ?
b101111101001110 .
b11 2
b11 =
b10 *
b10 4
b11 3
b10 +
b10 6
b110 7
b11 /
b11 5
1$
1!
#770001
0!
#773001
1&
b11011111000 %
0$
#773501
1!
#777001
0!
#779501
b111 (
b111 9
b110 7
b101 8
b100 )
b100 ;
b110 <
b110 1
b110 :
1$
#780501
b110 0
1!
#784001
0!
#786001
b1010110011010110 %
0$
#787501
1!
#791001
0!
#792501
b101 (
b101 9
b110 7
b110 8
b101 )
b101 ;
b110 <
b111 1
b111 :
1$
#794501
b111 0
1!
#798001
0!
#799001
b1100100010011100 %
0$
#801501
1!
#805001
0!
#805501
0&
bz %
b100 (
b100 9
b110 7
b111 8
b110 )
b110 ;
b110 <
b101 1
b101 :
1$
#808501
b101 0
1!
#812001
1"
0$
0!
#815501
b11011111000 .
b110 *
b110 4
b100 3
b11 +
b11 6
b110 7
b10 /
b10 5
1!
#818501
b110 7
b110 <
b11 '
b11 >
b110 ?
b10 2
b10 =
1$
#819001
0!
#822501
b1010110011010110 .
b111 *
b111 4
b101 3
b100 +
b100 6
b110 7
b110 /
b110 5
1!
#825001
0$
#826001
0!
#829501
b1100100010011100 .
b101 *
b101 4
b110 3
b101 +
b101 6
b110 7
b111 /
b111 5
1!
#831501
b110 7
b110 <
b101 '
b101 >
b110 ?
b111 2
b111 =
1$
#833001
0!
#836501
0"
b1110110001111001 .
b100 *
b100 4
b111 3
b110 +
b110 6
b110 7
1-
b101 /
b101 5
1!
#838001
1&
b1100110100011001 %
0$
#840001
0!
#843501
1!
#844501
0&
bz %
b1100110100011001 .
b1100 (
b1100 9
b110 7
b1000 8
b111 )
b111 ;
b110 <
b110 '
b110 >
b110 ?
b100 1
b100 :
b101 2
b101 =
1$
#847001
0!
#850501
0-
b100 0
1!
#851001
0$
#854001
1"
0!
#857501
0"
b110 <
b111 '
b111 >
b110 ?
b1101110001011101 .
b100 2
b100 =
b1100 *
b1100 4
b1000 3
b111 +
b111 6
b110 7
1-
b100 /
b100 5
1$
1!
#861001
0!
#864001
1&
b100001001100 %
0$
#864501
1!
#868001
0!
#870501
0&
bz %
b100001001100 .
b1101 (
b1101 9
b110 7
b1001 8
b1000 )
b1000 ;
b110 <
b1100 1
b1100 :
1$
#871501
0-
b1100 0
1!
#875001
1"
0!
#877001
0$
#878501
0"
b10101110010001 .
b1101 *
b1101 4
b1001 3
b1000 +
b1000 6
b110 7
1-
b1100 /
b1100 5
1!
#882001
0!
#883501
b110 7
b110 <
b1000 '
b1000 >
b110 ?
b1100 2
b1100 =
1$
#885501
1!
#889001
0!
#890001
1&
b1000100000011001 %
0$
#892501
1!
#896001
0!
#896501
b1000100000011001 .
b1111 (
b1111 9
b110 7
b1010 8
b1001 )
b1001 ;
b110 <
b1101 1
b1101 :
1$
#899501
0-
b1101 0
1!
#903001
b1010100010111010 %
0$
0!
#906501
1!
#909501
b1110 (
b1110 9
b110 7
b1011 8
b1010 )
b1010 ;
b110 <
b1111 1
b1111 :
1$
#910001
0!
#913501
b1111 0
1!
#916001
b111010111100111 %
0$
#917001
0!
#920501
1!
#922501
0&
bz %
b1010 (
b1010 9
b110 7
b1100 8
b1011 )
b1011 ;
b110 <
b1110 1
b1110 :
1$
#924001
1"
0!
#927501
b1010100010111010 .
b1110 0
b1111 *
b1111 4
b1010 3
b1001 +
b1001 6
b110 7
b1101 /
b1101 5
1!
#929001
0$
#931001
0!
#934501
0"
b111010111100111 .
b1110 *
b1110 4
b1011 3
b1010 +
b1010 6
b110 7
b1111 /
b1111 5
1!
#935501
b110 7
b110 <
b1010 '
b1010 >
b110 ?
b1111 2
b1111 =
1$
#938001
0!
#941501
1!
#942001
1&
b1101000100110 %
0$
#945001
0!
#948501
b1011 (
b1011 9
b110 7
b1101 8
b1100 )
b1100 ;
b110 <
b1010 1
b1010 :
1$
1!
#952001
0!
#955001
b1000011111101010 %
0$
#955501
b1010 0
1!
#959001
0!
#961501
0&
bz %
b1001 (
b1001 9
b110 7
b1110 8
b1101 )
b1101 ;
b110 <
b1011 1
b1011 :
1$
#962501
b1011 0
1!
#966001
1"
0!
#968001
0$
#969501
b1101000100110 .
b1010 *
b1010 4
b1100 3
b1011 +
b1011 6
b110 7
b1110 /
b1110 5
1!
#973001
0!
#974501
b110 7
b110 <
b1011 '
b1011 >
b110 ?
b1110 2
b1110 =
1$
#976501
b1000011111101010 .
b1011 *
b1011 4
b1101 3
b1100 +
b1100 6
b110 7
b1010 /
b1010 5
1!
#980001
0!
#981001
0$
#983501
0"
b1000001100001110 .
b1001 *
b1001 4
b1110 3
b1101 +
b1101 6
b110 7
1-
b1011 /
b1011 5
1!
#987001
0!
#987501
b110 7
b110 <
b1101 '
b1101 >
b110 ?
b1011 2
b1011 =
1$
#990501
1!
#994001
1&
b1010011001001 %
0$
0!
#997501
1!
#1000501
b1010011001001 .
b1000 (
b1000 9
b110 7
b1111 8
b1110 )
b1110 ;
b110 <
b1001 1
b1001 :
1$
#1001001
0!
#1004501
0-
b1001 0
1!
#1007001
b11110011010000 %
0$
#1008001
0!
#1011501
1!
#1013501
b11000 (
b11000 9
b110 7
b10000 8
b1111 )
b1111 ;
b110 <
b1000 1
b1000 :
1$
#1015001
0!
#1018501
b1000 0
1!
#1020001
b1110011100111000 %
0$
#1022001
0!
#1025501
1!
#1026501
b11001 (
b11001 9
b110 7
b10001 8
b10000 )
b10000 ;
b110 <
b11000 1
b11000 :
1$
#1029001
0!
#1032501
b11000 0
1!
#1033001
b1110010001110000 %
0$
#1036001
0!
#1039501
b11011 (
b11011 9
b110 7
b10010 8
b10001 )
b10001 ;
b110 <
b11001 1
b11001 :
1$
1!
#1043001
0!
#1046001
b110101110110000 %
0$
#1046501
b11001 0
1!
#1050001
0!
#1052501
b11010 (
b11010 9
b110 7
b10011 8
b10010 )
b10010 ;
b110 <
b11011 1
b11011 :
1$
#1053501
b11011 0
1!
#1057001
0!
#1059001
b11000010100000 %
0$
#1060501
1!
#1064001
0!
#1065501
b11110 (
b11110 9
b110 7
b10100 8
b10011 )
b10011 ;
b110 <
b11010 1
b11010 :
1$
#1067501
b11010 0
1!
#1071001
0!
#1072001
b101110010000111 %
0$
#1074501
1!
#1078001
0!
#1078501
b11111 (
b11111 9
b110 7
b10101 8
b10100 )
b10100 ;
b110 <
b11110 1
b11110 :
1$
#1081501
b11110 0
1!
#1085001
b11100001010 %
0$
0!
#1088501
1!
#1091501
0&
bz %
b11101 (
b11101 9
b110 7
b10110 8
b10101 )
b10101 ;
b110 <
b11111 1
b11111 :
1$
#1092001
1"
0!
#1095501
0"
b11110011010000 .
b11111 0
b1000 *
b1000 4
b1111 3
b1110 +
b1110 6
b110 7
b1001 /
b1001 5
1!
#1098001
1&
b11001110101010 %
0$
#1099001
0!
#1102501
1!
#1104501
0&
bz %
b11100 (
b11100 9
b110 7
b10111 8
b10110 )
b10110 ;
b110 <
b1110 '
b1110 >
b110 ?
b11101 1
b11101 :
b1001 2
b1001 =
1$
#1106001
1"
0!
#1109501
0"
b1110011100111000 .
b11101 0
b11000 *
b11000 4
b10000 3
b1111 +
b1111 6
b110 7
b1000 /
b1000 5
1!
#1111001
1&
b1000100000100001 %
0$
#1113001
0!
#1116501
1!
#1117501
0&
bz %
b10100 (
b10100 9
b110 7
b11000 8
b10111 )
b10111 ;
b110 <
b1111 '
b1111 >
b110 ?
b11100 1
b11100 :
b1000 2
b1000 =
1$
#1120001
1"
0!
#1123501
0"
b1110010001110000 .
b11100 0
b11001 *
b11001 4
b10001 3
b10000 +
b10000 6
b110 7
b11000 /
b11000 5
1!
#1124001
1&
b10111000101000 %
0$
#1127001
0!
#1130501
0&
bz %
b10101 (
b10101 9
b110 7
b11001 8
b11000 )
b11000 ;
b110 <
b10000 '
b10000 >
b110 ?
b10100 1
b10100 :
b11000 2
b11000 =
1$
1!
#1134001
1"
0!
#1137001
0$
#1137501
b110101110110000 .
b10100 0
b11011 *
b11011 4
b10010 3
b10001 +
b10001 6
b110 7
b11001 /
b11001 5
1!
#1141001
0!
#1143501
b110 7
b110 <
b10001 '
b10001 >
b110 ?
b11001 2
b11001 =
1$
#1144501
b11000010100000 .
b11010 *
b11010 4
b10011 3
b10010 +
b10010 6
b110 7
b11011 /
b11011 5
1!
#1148001
0!
#1150001
0$
#1151501
b101110010000111 .
b11110 *
b11110 4
b10100 3
b10011 +
b10011 6
b110 7
b11010 /
b11010 5
1!
#1155001
0!
#1156501
b110 7
b110 <
b10011 '
b10011 >
b110 ?
b11010 2
b11010 =
1$
#1158501
0"
b11100001010 .
b11111 *
b11111 4
b10101 3
b10100 +
b10100 6
b110 7
b11110 /
b11110 5
1!
#1162001
0!
#1163001
1&
b1111111000100100 %
0$
#1165501
1!
#1169001
0!
#1169501
0&
bz %
b10111 (
b10111 9
b110 7
b11010 8
b11001 )
b11001 ;
b110 <
b10100 '
b10100 >
b110 ?
b10101 1
b10101 :
b11110 2
b11110 =
1$
#1172501
b10101 0
1!
#1176001
1"
0$
0!
#1179501
b11001110101010 .
b11101 *
b11101 4
b10110 3
b10101 +
b10101 6
b110 7
b11111 /
b11111 5
1!
#1182501
b110 7
b110 <
b10101 '
b10101 >
b110 ?
b11111 2
b11111 =
1$
#1183001
0!
#1186501
0"
b1000100000100001 .
b11100 *
b11100 4
b10111 3
b10110 +
b10110 6
b110 7
b11101 /
b11101 5
1!
