src/bin2gray.sv
`timescale 1ns / 1ps
`default_nettype none

module bin2gray
    #(
        parameter BINARY_WIDTH = 8
    )
    (
        input wire [BINARY_WIDTH - 1: 0] binary,
        output reg [BINARY_WIDTH - 1: 0] gray
    );

    always_comb begin 
        gray <= binary >> 1 ^ binary;
    end

endmodule

src/gray2bin.sv
`timescale 1ns / 1ps
`default_nettype none

module gray2bin
    #(
        parameter BINARY_WIDTH = 8
    )
    (
        output reg [BINARY_WIDTH - 1: 0] binary,
        input wire [BINARY_WIDTH - 1: 0] gray
    );

    integer i;

    always_comb begin
        for(i = 0; i < BINARY_WIDTH; i++) begin
            binary[i] <= ^(gray >> i);
        end
    end

endmodule

src/dual_port_fifo.sv
`timescale 1ns / 1ps
`default_nettype none

module dual_port_fifo
    #(
        parameter DATA_WIDTH = 16,
        parameter FIFO_DEPTH = 32
    )(
        input wire wr_clk,
        input wire wr_en,
        input wire [DATA_WIDTH - 1: 0] wr_data,
        output wire full,

        input wire rd_clk,
        output wire rd_en,
        output reg [DATA_WIDTH - 1: 0] rd_data,
        output wire empty,

        input wire reset
    );

    `ifdef COCOTB_SIM
    initial begin
        $dumpfile("dual_port_fifo.vcd");
        $dumpvars(0, dual_port_fifo);
    end
    `endif

    localparam POINTER_WIDTH = $clog2(FIFO_DEPTH);

    logic [DATA_WIDTH - 1: 0] fifo_data [FIFO_DEPTH - 1: 0];

    logic [DATA_WIDTH - 1: 0] read_head;


    //READ CLOCK DOMAIN
    logic [POINTER_WIDTH-1:0] rd_pointer_binary;
    logic [POINTER_WIDTH-1:0] rd_pointer_gray;   
    logic [POINTER_WIDTH-1:0] rd_pointer_gray_incremented;   
    logic [POINTER_WIDTH-1:0] rdcdc_wr_pointer_gray;

    gray2bin #(.BINARY_WIDTH(POINTER_WIDTH))
        rd_side_g2b(.gray(rd_pointer_gray), .binary(rd_pointer_binary));
    
    bin2gray #(.BINARY_WIDTH(POINTER_WIDTH))
        rd_side_b2g(.gray(rd_pointer_gray_incremented), .binary(rd_pointer_binary + 1'b1));
    
    assign empty = rdcdc_wr_pointer_gray == rd_pointer_gray;

    always @(posedge rd_clk, posedge reset) begin
        //CDC of wr pointer
        rdcdc_wr_pointer_gray <= wr_pointer_gray;
        if(reset) begin
            rd_pointer_gray <= 0;
        end else begin
            if(rd_en & ~empty) begin
                rd_data <= fifo_data[rd_pointer_binary];
                rd_pointer_gray <= rd_pointer_gray_incremented;
            end
        end
    end


    ///WRITE CLOCK DOMAIN
    logic [POINTER_WIDTH-1:0] wr_pointer_binary;
    logic [POINTER_WIDTH-1:0] wr_pointer_gray;   
    logic [POINTER_WIDTH-1:0] wr_pointer_gray_incremented;   
    logic [POINTER_WIDTH-1:0] wrcdc_rd_pointer_gray;
    
    gray2bin #(.BINARY_WIDTH(POINTER_WIDTH))
        wr_side_g2b(.gray(wr_pointer_gray), .binary(wr_pointer_binary));
    
    bin2gray #(.BINARY_WIDTH(POINTER_WIDTH))
        wr_side_b2g(.gray(wr_pointer_gray_incremented), .binary(wr_pointer_binary + 1'b1));

    assign full = wrcdc_rd_pointer_gray == wr_pointer_gray_incremented;

    always @(posedge wr_clk, posedge reset) begin
        wrcdc_rd_pointer_gray <= rd_pointer_gray;
        if(reset) begin
            wr_pointer_gray <= 0;
        end else begin
            if(wr_en & ~full) begin
                fifo_data[wr_pointer_binary] <= wr_data;
                wr_pointer_gray <= wr_pointer_gray_incremented;
            end
        end
    end
endmodule

src_test/fifo/dual_port_fifo.vcd
$date
	Sun Aug 15 16:29:06 2021
$end
$version
	Icarus Verilog
$end
$timescale
	1ps
$end
$scope module dual_port_fifo $end
$var wire 1 ! rd_clk $end
$var wire 1 " rd_en $end
$var wire 1 # reset $end
$var wire 1 $ wr_clk $end
$var wire 16 % wr_data [15:0] $end
$var wire 1 & wr_en $end
$var wire 5 ' wr_pointer_gray_incremented [4:0] $end
$var wire 5 ( wr_pointer_binary [4:0] $end
$var wire 5 ) rd_pointer_gray_incremented [4:0] $end
$var wire 5 * rd_pointer_binary [4:0] $end
$var wire 1 + full $end
$var wire 1 , empty $end
$var reg 16 - rd_data [15:0] $end
$var reg 5 . rd_pointer_gray [4:0] $end
$var reg 5 / rdcdc_wr_pointer_gray [4:0] $end
$var reg 5 0 wr_pointer_gray [4:0] $end
$var reg 5 1 wrcdc_rd_pointer_gray [4:0] $end
$scope module rd_side_b2g $end
$var wire 5 2 binary [4:0] $end
$var reg 5 3 gray [4:0] $end
$upscope $end
$scope module rd_side_g2b $end
$var wire 5 4 gray [4:0] $end
$var reg 5 5 binary [4:0] $end
$var integer 32 6 i [31:0] $end
$upscope $end
$scope module wr_side_b2g $end
$var wire 5 7 binary [4:0] $end
$var reg 5 8 gray [4:0] $end
$upscope $end
$scope module wr_side_g2b $end
$var wire 5 9 gray [4:0] $end
$var reg 5 : binary [4:0] $end
$var integer 32 ; i [31:0] $end
$upscope $end
$upscope $end
$enddefinitions $end
#0
$dumpvars
b101 ;
b0 :
b0 9
b1 8
b1 7
b101 6
b0 5
b0 4
b1 3
b1 2
bx 1
b0 0
bx /
b0 .
bx -
x,
x+
b0 *
b1 )
b0 (
b1 '
z&
bz %
1$
1#
0"
1!
$end
#1500
0!
#3000
1,
b0 /
1!
#4500
0!
#5000
0$
#6000
1!
#7500
0!
#9000
1!
#10000
0#
1&
b110011100101111 %
0+
b0 1
1$
#10500
0!
#12000
1!
#13500
0!
#15000
0$
1!
#16500
0!
#18000
1!
#19500
0!
#20000
b1001100111111001 %
b11 '
b11 8
b101 6
b10 7
b1 (
b1 :
b101 ;
b1 0
b1 9
1$
#21000
0,
b1 /
1!
#22500
0!
#24000
1!
#25000
0$
#25500
0!
#27000
1!
#28500
0!
#30000
b1110110100110100 %
b10 '
b10 8
b101 6
b11 7
b10 (
b10 :
b101 ;
b11 0
b11 9
1$
1!
#31500
0!
#33000
b11 /
1!
#34500
0!
#35000
0$
#36000
1!
#37500
0!
#39000
1!
#40000
b100000101 %
b110 '
b110 8
b101 6
b100 7
b11 (
b11 :
b101 ;
b10 0
b10 9
1$
#40500
0!
#42000
b10 /
1!
#43500
0!
#45000
0$
1!
#46500
0!
#48000
1!
#49500
0!
#50000
b110011000110000 %
b111 '
b111 8
b101 6
b101 7
b100 (
b100 :
b101 ;
b110 0
b110 9
1$
#51000
b110 /
1!
#52500
0!
#54000
1!
#55000
0$
#55500
0!
#57000
1!
#58500
0!
#60000
b1100111110100100 %
b101 '
b101 8
b101 6
b110 7
b101 (
b101 :
b101 ;
b111 0
b111 9
1$
1!
#61500
0!
#63000
b111 /
1!
#64500
0!
#65000
0$
#66000
1!
#67500
0!
#69000
1!
#70000
b101111010000 %
b100 '
b100 8
b101 6
b111 7
b110 (
b110 :
b101 ;
b101 0
b101 9
1$
#70500
0!
#72000
b101 /
1!
#73500
0!
#75000
0$
1!
#76500
0!
#78000
1!
#79500
0!
#80000
b1010101111011 %
b1100 '
b1100 8
b101 6
b1000 7
b111 (
b111 :
b101 ;
b100 0
b100 9
1$
#81000
b100 /
1!
#82500
0!
#84000
1!
#85000
0$
#85500
0!
#87000
1!
#88500
0!
#90000
b1111101010100000 %
b1101 '
b1101 8
b101 6
b1001 7
b1000 (
b1000 :
b101 ;
b1100 0
b1100 9
1$
1!
#91500
0!
#93000
b1100 /
1!
#94500
0!
#95000
0$
#96000
1!
#97500
0!
#99000
1!
#100000
b1101001101001101 %
b1111 '
b1111 8
b101 6
b1010 7
b1001 (
b1001 :
b101 ;
b1101 0
b1101 9
1$
#100500
0!
#102000
b1101 /
1!
#103500
0!
#105000
0$
1!
#106500
0!
#108000
1!
#109500
0!
#110000
b11100100000101 %
b1110 '
b1110 8
b101 6
b1011 7
b1010 (
b1010 :
b101 ;
b1111 0
b1111 9
1$
#111000
b1111 /
1!
#112500
0!
#114000
1!
#115000
0$
#115500
0!
#117000
1!
#118500
0!
#120000
b1100101110000111 %
b1010 '
b1010 8
b101 6
b1100 7
b1011 (
b1011 :
b101 ;
b1110 0
b1110 9
1$
1!
#121500
0!
#123000
b1110 /
1!
#124500
0!
#125000
0$
#126000
1!
#127500
0!
#129000
1!
#130000
b111000001101010 %
b1011 '
b1011 8
b101 6
b1101 7
b1100 (
b1100 :
b101 ;
b1010 0
b1010 9
1$
#130500
0!
#132000
b1010 /
1!
#133500
0!
#135000
0$
1!
#136500
0!
#138000
1!
#139500
0!
#140000
b111110000100111 %
b1001 '
b1001 8
b101 6
b1110 7
b1101 (
b1101 :
b101 ;
b1011 0
b1011 9
1$
#141000
b1011 /
1!
#142500
0!
#144000
1!
#145000
0$
#145500
0!
#147000
1!
#148500
0!
#150000
b101000111101001 %
b1000 '
b1000 8
b101 6
b1111 7
b1110 (
b1110 :
b101 ;
b1001 0
b1001 9
1$
1!
#151500
0!
#153000
b1001 /
1!
#154500
0!
#155000
0$
#156000
1!
#157500
0!
#159000
1!
#160000
b111001010111011 %
b11000 '
b11000 8
b101 6
b10000 7
b1111 (
b1111 :
b101 ;
b1000 0
b1000 9
1$
#160500
0!
#162000
b1000 /
1!
#163500
0!
#165000
0$
1!
#166500
0!
#168000
1!
#169500
0!
#170000
b101000001000110 %
b11001 '
b11001 8
b101 6
b10001 7
b10000 (
b10000 :
b101 ;
b11000 0
b11000 9
1$
#171000
b11000 /
1!
#172500
0!
#174000
1!
#175000
0$
#175500
0!
#177000
1!
#178500
0!
#180000
b1010100111111001 %
b11011 '
b11011 8
b101 6
b10010 7
b10001 (
b10001 :
b101 ;
b11001 0
b11001 9
1$
1!
#181500
0!
#183000
b11001 /
1!
#184500
0!
#185000
0$
#186000
1!
#187500
0!
#189000
1!
#190000
b110101001111001 %
b11010 '
b11010 8
b101 6
b10011 7
b10010 (
b10010 :
b101 ;
b11011 0
b11011 9
1$
#190500
0!
#192000
b11011 /
1!
#193500
0!
#195000
0$
1!
#196500
0!
#198000
1!
#199500
0!
#200000
b1000010001100111 %
b11110 '
b11110 8
b101 6
b10100 7
b10011 (
b10011 :
b101 ;
b11010 0
b11010 9
1$
#201000
b11010 /
1!
#202500
0!
#204000
1!
#205000
0$
#205500
0!
#207000
1!
#208500
0!
#210000
b110000110110010 %
b11111 '
b11111 8
b101 6
b10101 7
b10100 (
b10100 :
b101 ;
b11110 0
b11110 9
1$
1!
#211500
0!
#213000
b11110 /
1!
#214500
0!
#215000
0$
#216000
1!
#217500
0!
#219000
1!
#220000
b1001011000010010 %
b11101 '
b11101 8
b101 6
b10110 7
b10101 (
b10101 :
b101 ;
b11111 0
b11111 9
1$
#220500
0!
#222000
b11111 /
1!
#223500
0!
#225000
0$
1!
#226500
0!
#228000
1!
#229500
0!
#230000
b10111010000000 %
b11100 '
b11100 8
b101 6
b10111 7
b10110 (
b10110 :
b101 ;
b11101 0
b11101 9
1$
#231000
b11101 /
1!
#232500
0!
#234000
1!
#235000
0$
#235500
0!
#237000
1!
#238500
0!
#240000
b100001011000111 %
b10100 '
b10100 8
b101 6
b11000 7
b10111 (
b10111 :
b101 ;
b11100 0
b11100 9
1$
1!
#241500
0!
#243000
b11100 /
1!
#244500
0!
#245000
0$
#246000
1!
#247500
0!
#249000
1!
#250000
b11001001111 %
b10101 '
b10101 8
b101 6
b11001 7
b11000 (
b11000 :
b101 ;
b10100 0
b10100 9
1$
#250500
0!
#252000
b10100 /
1!
#253500
0!
#255000
0$
1!
#256500
0!
#258000
1!
#259500
0!
#260000
b1101010001011011 %
b10111 '
b10111 8
b101 6
b11010 7
b11001 (
b11001 :
b101 ;
b10101 0
b10101 9
1$
#261000
b10101 /
1!
#262500
0!
#264000
1!
#265000
0$
#265500
0!
#267000
1!
#268500
0!
#270000
b101010110110001 %
b10110 '
b10110 8
b101 6
b11011 7
b11010 (
b11010 :
b101 ;
b10111 0
b10111 9
1$
1!
#271500
0!
#273000
b10111 /
1!
#274500
0!
#275000
0$
#276000
1!
#277500
0!
#279000
1!
#280000
b101110111011101 %
b10010 '
b10010 8
b101 6
b11100 7
b11011 (
b11011 :
b101 ;
b10110 0
b10110 9
1$
#280500
0!
#282000
b10110 /
1!
#283500
0!
#285000
0$
1!
#286500
0!
#288000
1!
#289500
0!
#290000
b10001000000110 %
b10011 '
b10011 8
b101 6
b11101 7
b11100 (
b11100 :
b101 ;
b10010 0
b10010 9
1$
#291000
b10010 /
1!
#292500
0!
#294000
1!
#295000
0$
#295500
0!
#297000
1!
#298500
0!
#300000
b1110011101001101 %
b10001 '
b10001 8
b101 6
b11110 7
b11101 (
b11101 :
b101 ;
b10011 0
b10011 9
1$
1!
#301500
0!
#303000
b10011 /
1!
#304500
0!
#305000
0$
#306000
1!
#307500
0!
#309000
1!
#310000
b1000000111101001 %
b10000 '
b10000 8
b101 6
b11111 7
b11110 (
b11110 :
b101 ;
b10001 0
b10001 9
1$
#310500
0!
#312000
b10001 /
1!
#313500
0!
#315000
0$
1!
#316500
0!
#318000
1!
#319500
0!
#320000
b101010011010010 %
1+
b0 '
b0 8
b101 6
b0 7
b11111 (
b11111 :
b101 ;
b10000 0
b10000 9
1$
#321000
b10000 /
1!
#322500
0!
#324000
1!
#325000
0$
#325500
0!
#327000
1!
#328500
0!
#330000
0&
1$
1!
#331500
0!
#333000
1"
1!
#334500
0!
#335000
0$
#336000
b11 )
b11 3
b10 2
b1 *
b1 5
b101 6
b1 .
b1 4
b110011100101111 -
1!
#337500
0!
#339000
b10 )
b10 3
b11 2
b10 *
b10 5
b101 6
b11 .
b11 4
b1001100111111001 -
1!
#340000
0+
b11 1
1$
#340500
0!
#342000
b110 )
b110 3
b100 2
b11 *
b11 5
b101 6
b10 .
b10 4
b1110110100110100 -
1!
#343500
0!
#345000
b111 )
b111 3
b101 2
b100 *
b100 5
b101 6
b110 .
b110 4
b100000101 -
0$
1!
#346500
0!
#348000
b101 )
b101 3
b110 2
b101 *
b101 5
b101 6
b111 .
b111 4
b110011000110000 -
1!
#349500
0!
#350000
b111 1
1$
#351000
b100 )
b100 3
b111 2
b110 *
b110 5
b101 6
b101 .
b101 4
b1100111110100100 -
1!
#352500
0!
#354000
b1100 )
b1100 3
b1000 2
b111 *
b111 5
b101 6
b100 .
b100 4
b101111010000 -
1!
#355000
0$
#355500
0!
#357000
b1101 )
b1101 3
b1001 2
b1000 *
b1000 5
b101 6
b1100 .
b1100 4
b1010101111011 -
1!
#358500
0!
#360000
b1111 )
b1111 3
b1010 2
b1001 *
b1001 5
b101 6
b1100 1
b1101 .
b1101 4
b1111101010100000 -
1$
1!
#361500
0!
#363000
b1110 )
b1110 3
b1011 2
b1010 *
b1010 5
b101 6
b1111 .
b1111 4
b1101001101001101 -
1!
#364500
0!
#365000
0$
#366000
b1010 )
b1010 3
b1100 2
b1011 *
b1011 5
b101 6
b1110 .
b1110 4
b11100100000101 -
1!
#367500
0!
#369000
b1011 )
b1011 3
b1101 2
b1100 *
b1100 5
b101 6
b1010 .
b1010 4
b1100101110000111 -
1!
#370000
b1010 1
1$
#370500
0!
#372000
b1001 )
b1001 3
b1110 2
b1101 *
b1101 5
b101 6
b1011 .
b1011 4
b111000001101010 -
1!
#373500
0!
#375000
b1000 )
b1000 3
b1111 2
b1110 *
b1110 5
b101 6
b1001 .
b1001 4
b111110000100111 -
0$
1!
#376500
0!
#378000
b11000 )
b11000 3
b10000 2
b1111 *
b1111 5
b101 6
b1000 .
b1000 4
b101000111101001 -
1!
#379500
0!
#380000
b1000 1
1$
#381000
b11001 )
b11001 3
b10001 2
b10000 *
b10000 5
b101 6
b11000 .
b11000 4
b111001010111011 -
1!
#382500
0!
#384000
b11011 )
b11011 3
b10010 2
b10001 *
b10001 5
b101 6
b11001 .
b11001 4
b101000001000110 -
1!
#385000
0$
#385500
0!
#387000
b11010 )
b11010 3
b10011 2
b10010 *
b10010 5
b101 6
b11011 .
b11011 4
b1010100111111001 -
1!
#388500
0!
#390000
b11110 )
b11110 3
b10100 2
b10011 *
b10011 5
b101 6
b11011 1
b11010 .
b11010 4
b110101001111001 -
1$
1!
#391500
0!
#393000
b11111 )
b11111 3
b10101 2
b10100 *
b10100 5
b101 6
b11110 .
b11110 4
b1000010001100111 -
1!
#394500
0!
#395000
0$
#396000
b11101 )
b11101 3
b10110 2
b10101 *
b10101 5
b101 6
b11111 .
b11111 4
b110000110110010 -
1!
#397500
0!
#399000
b11100 )
b11100 3
b10111 2
b10110 *
b10110 5
b101 6
b11101 .
b11101 4
b1001011000010010 -
1!
#400000
b11101 1
1$
#400500
0!
#402000
b10100 )
b10100 3
b11000 2
b10111 *
b10111 5
b101 6
b11100 .
b11100 4
b10111010000000 -
1!
#403500
0!
#405000
b10101 )
b10101 3
b11001 2
b11000 *
b11000 5
b101 6
b10100 .
b10100 4
b100001011000111 -
0$
1!
#406500
0!
#408000
b10111 )
b10111 3
b11010 2
b11001 *
b11001 5
b101 6
b10101 .
b10101 4
b11001001111 -
1!
#409500
0!
#410000
b10101 1
1$
#411000
b10110 )
b10110 3
b11011 2
b11010 *
b11010 5
b101 6
b10111 .
b10111 4
b1101010001011011 -
1!
#412500
0!
#414000
b10010 )
b10010 3
b11100 2
b11011 *
b11011 5
b101 6
b10110 .
b10110 4
b101010110110001 -
1!
#415000
0$
#415500
0!
#417000
b10011 )
b10011 3
b11101 2
b11100 *
b11100 5
b101 6
b10010 .
b10010 4
b101110111011101 -
1!
#418500
0!
#420000
b10001 )
b10001 3
b11110 2
b11101 *
b11101 5
b101 6
b10010 1
b10011 .
b10011 4
b10001000000110 -
1$
1!
#421500
0!
#423000
b10000 )
b10000 3
b11111 2
b11110 *
b11110 5
b101 6
b10001 .
b10001 4
b1110011101001101 -
1!
#424500
0!
#425000
0$
#426000
b0 )
b0 3
b0 2
b11111 *
b11111 5
b101 6
1,
b10000 .
b10000 4
b1000000111101001 -
1!
