uart/src/uart_rx.sv
`timescale 1ns / 1ps
`default_nettype none
//////////////////////////////////////////////////////////////////////////////////
// Company: 
// Engineer: 
// 
// Create Date: 07/29/2021 10:17:57 PM
// Design Name: 
// Module Name: uart_rx
// Project Name: 
// Target Devices: 
// Tool Versions: 
// Description: 
// 
// Dependencies: 
// 
// Revision:
// Revision 0.01 - File Created
// Additional Comments:
// 
//////////////////////////////////////////////////////////////////////////////////

module uart_rx
    #(   parameter CLOCK_FREQUENCY = 12_000_000,
         parameter BAUD_RATE = 115_200,
         parameter PARITY_BIT = 0
     )(
        input wire uart_clk,
        input wire uart_in,
        input wire reset,

        output reg [7:0] data,
        output reg data_out_strobe
    );
    
    localparam CLOCKS_PER_BAUD = CLOCK_FREQUENCY/BAUD_RATE;

    localparam DELAY_WIDTH = $clog2(CLOCK_FREQUENCY * 3/2);

    //for easier verification
    `ifdef COCOTB_SIM
        wire read_strobe;
        assign read_strobe = clock_delay == 0;
    `endif

    reg receiving_state = 0;
    reg returned_high = 1;
    reg [2:0] byte_counter = 0;
    reg [DELAY_WIDTH: 0] clock_delay = 0;

    always @(posedge uart_clk) begin
        if(reset) begin     
            data_out_strobe <= 0;
            receiving_state <= 0;
            byte_counter <= 0;
            clock_delay <= 0;
            returned_high <= 1;
        end else begin
        //if we are receiving
            if(receiving_state) begin
                if(clock_delay == 0) begin
                    data[byte_counter] <= uart_in;                    
                    clock_delay <= CLOCKS_PER_BAUD - 1'b1;
                    byte_counter <= byte_counter + 1'b1;
                    if(byte_counter == 3'b111) begin
                        receiving_state <= 1'b0;
                        returned_high <= 0;
                    end
                end else begin
                    clock_delay <= clock_delay - 1'b1;
                end
            end else begin
            //set receiving state, so we're receiving bits
            //delay by one clock cycle
                if(returned_high) begin
                    if(uart_in == 0) begin
                        receiving_state <= 1'b1;
                        //there is a chance that the edges of our clock fall close to the bit edges
                        //so we wait one extra clock to stop any skew
                        clock_delay <= (CLOCKS_PER_BAUD + CLOCKS_PER_BAUD/2); 
                        byte_counter <= 3'b000;
                    end
                end else begin
                    if(uart_in) begin
                        returned_high <= 1'b1;
                        data_out_strobe <= 1'b1;
                    end
                end
            end
        end
        if(data_out_strobe) begin
            data_out_strobe <= 0;
        end
    end
    
endmodule

uart/test/uart_rx/uart_rx_tb.sv
`timescale 1ns / 1ps
`default_nettype none

module uart_rx_tb
    #(   
        parameter CLOCK_FREQUENCY = 20_000,
        parameter BAUD_RATE = 4_000,
        parameter PARITY_BIT = 0
    )(
        input wire i_uart_clk,
        input wire i_uart_in,
        input wire i_reset,

        output reg[7:0] o_data,
        output reg o_data_out_strobe
    );

    initial begin
        $dumpfile("uart_rx_tb.vcd");
        $dumpvars(0, uart_rx_tb);
    end

    uart_rx #(.CLOCK_FREQUENCY(CLOCK_FREQUENCY),
            .BAUD_RATE(BAUD_RATE),
            .PARITY_BIT(PARITY_BIT)) 
        uart_rx_inst(
        .uart_clk(i_uart_clk),
        .uart_in(i_uart_in),
        .reset(i_reset),
        .data(o_data),
        .data_out_strobe(o_data_out_strobe));

endmodule

uart/test/uart_rx/uart_rx_tb.vcd
$date
	Sat Sep  4 16:42:13 2021
$end
$version
	Icarus Verilog
$end
$timescale
	1ps
$end
$scope module uart_rx_tb $end
$var wire 1 ! i_reset $end
$var wire 1 " i_uart_clk $end
$var wire 1 # i_uart_in $end
$var wire 1 $ o_data_out_strobe $end
$var wire 8 % o_data [7:0] $end
$scope module uart_rx_inst $end
$var wire 1 ! reset $end
$var wire 1 " uart_clk $end
$var wire 1 # uart_in $end
$var wire 1 & read_strobe $end
$var reg 3 ' byte_counter [2:0] $end
$var reg 16 ( clock_delay [15:0] $end
$var reg 8 ) data [7:0] $end
$var reg 1 $ data_out_strobe $end
$var reg 1 * receiving_state $end
$var reg 1 + returned_high $end
$upscope $end
$upscope $end
$enddefinitions $end
#0
$dumpvars
1+
0*
bx )
b0 (
b0 '
1&
bx %
x$
1#
1"
1!
$end
#25000000
0"
#50000000
0!
0#
0$
1"
#75000000
0"
#100000000
0&
b111 (
1*
1"
#125000000
0"
#150000000
b110 (
1"
#175000000
0"
#200000000
b101 (
1"
#225000000
0"
#250000000
b100 (
1"
#275000000
0"
#300000000
b11 (
1"
#325000000
0"
#350000000
b10 (
1"
#375000000
0"
#400000000
b1 (
1"
#425000000
0"
#450000000
1&
b0 (
1"
#475000000
0"
#500000000
b1 '
0&
b100 (
bx0 %
bx0 )
1"
#525000000
0"
#550000000
b11 (
1"
#575000000
0"
#600000000
b10 (
1"
#625000000
0"
#650000000
b1 (
1"
#675000000
0"
#700000000
1&
b0 (
1"
#725000000
0"
#750000000
b10 '
0&
b100 (
bx00 %
bx00 )
1"
#775000000
0"
#800000000
b11 (
1"
#825000000
0"
#850000000
b10 (
1"
#875000000
0"
#900000000
b1 (
1"
#925000000
0"
#950000000
1&
b0 (
1"
#975000000
0"
#1000000000
b11 '
0&
b100 (
bx000 %
bx000 )
1"
#1025000000
0"
#1050000000
b11 (
1"
#1075000000
0"
#1100000000
b10 (
1"
#1125000000
0"
#1150000000
b1 (
1"
#1175000000
0"
#1200000000
1&
b0 (
1"
#1225000000
0"
#1250000000
b100 '
0&
b100 (
bx0000 %
bx0000 )
1"
#1275000000
0"
#1300000000
b11 (
1"
#1325000000
0"
#1350000000
b10 (
1"
#1375000000
0"
#1400000000
b1 (
1"
#1425000000
0"
#1450000000
1&
b0 (
1"
#1475000000
0"
#1500000000
b101 '
0&
b100 (
bx00000 %
bx00000 )
1"
#1525000000
0"
#1550000000
b11 (
1"
#1575000000
0"
#1600000000
b10 (
1"
#1625000000
0"
#1650000000
b1 (
1"
#1675000000
0"
#1700000000
1&
b0 (
1"
#1725000000
0"
#1750000000
b110 '
0&
b100 (
bx000000 %
bx000000 )
1"
#1775000000
0"
#1800000000
b11 (
1"
#1825000000
0"
#1850000000
b10 (
1"
#1875000000
0"
#1900000000
b1 (
1"
#1925000000
0"
#1950000000
1&
b0 (
1"
#1975000000
0"
#2000000000
b111 '
0&
b100 (
bx0000000 %
bx0000000 )
1"
#2025000000
0"
#2050000000
b11 (
1"
#2075000000
0"
#2100000000
b10 (
1"
#2125000000
0"
#2150000000
b1 (
1"
#2175000000
0"
#2200000000
1&
b0 (
1"
#2225000000
0"
#2250000000
0+
0*
b0 '
0&
b100 (
b0 %
b0 )
1"
#2275000000
0"
#2300000000
1$
1+
0#
1"
#2325000000
0"
#2350000000
0$
b111 (
1*
1"
#2375000000
0"
#2400000000
b110 (
1"
#2425000000
0"
#2450000000
b101 (
1"
#2475000000
0"
#2500000000
b100 (
1"
#2525000000
0"
#2550000000
b11 (
1#
1"
#2575000000
0"
#2600000000
b10 (
1"
#2625000000
0"
#2650000000
b1 (
1"
#2675000000
0"
#2700000000
1&
b0 (
1"
#2725000000
0"
#2750000000
b1 '
0&
b100 (
b1 %
b1 )
1"
#2775000000
0"
#2800000000
b11 (
0#
1"
#2825000000
0"
#2850000000
b10 (
1"
#2875000000
0"
#2900000000
b1 (
1"
#2925000000
0"
#2950000000
1&
b0 (
1"
#2975000000
0"
#3000000000
b10 '
0&
b100 (
1"
#3025000000
0"
#3050000000
b11 (
1"
#3075000000
0"
#3100000000
b10 (
1"
#3125000000
0"
#3150000000
b1 (
1"
#3175000000
0"
#3200000000
1&
b0 (
1"
#3225000000
0"
#3250000000
b11 '
0&
b100 (
1"
#3275000000
0"
#3300000000
b11 (
1"
#3325000000
0"
#3350000000
b10 (
1"
#3375000000
0"
#3400000000
b1 (
1"
#3425000000
0"
#3450000000
1&
b0 (
1"
#3475000000
0"
#3500000000
b100 '
0&
b100 (
1"
#3525000000
0"
#3550000000
b11 (
1"
#3575000000
0"
#3600000000
b10 (
1"
#3625000000
0"
#3650000000
b1 (
1"
#3675000000
0"
#3700000000
1&
b0 (
1"
#3725000000
0"
#3750000000
b101 '
0&
b100 (
1"
#3775000000
0"
#3800000000
b11 (
1"
#3825000000
0"
#3850000000
b10 (
1"
#3875000000
0"
#3900000000
b1 (
1"
#3925000000
0"
#3950000000
1&
b0 (
1"
#3975000000
0"
#4000000000
b110 '
0&
b100 (
1"
#4025000000
0"
#4050000000
b11 (
1"
#4075000000
0"
#4100000000
b10 (
1"
#4125000000
0"
#4150000000
b1 (
1"
#4175000000
0"
#4200000000
1&
b0 (
1"
#4225000000
0"
#4250000000
b111 '
0&
b100 (
1"
#4275000000
0"
#4300000000
b11 (
1"
#4325000000
0"
#4350000000
b10 (
1"
#4375000000
0"
#4400000000
b1 (
1"
#4425000000
0"
#4450000000
1&
b0 (
1"
#4475000000
0"
#4500000000
0+
0*
b0 '
0&
b100 (
1"
#4525000000
0"
#4550000000
1$
1+
0#
1"
#4575000000
0"
#4600000000
0$
b111 (
1*
1"
#4625000000
0"
#4650000000
b110 (
1"
#4675000000
0"
#4700000000
b101 (
1"
#4725000000
0"
#4750000000
b100 (
1"
#4775000000
0"
#4800000000
b11 (
1"
#4825000000
0"
#4850000000
b10 (
1"
#4875000000
0"
#4900000000
b1 (
1"
#4925000000
0"
#4950000000
1&
b0 (
1"
#4975000000
0"
#5000000000
b1 '
0&
b100 (
b0 %
b0 )
1"
#5025000000
0"
#5050000000
b11 (
1#
1"
#5075000000
0"
#5100000000
b10 (
1"
#5125000000
0"
#5150000000
b1 (
1"
#5175000000
0"
#5200000000
1&
b0 (
1"
#5225000000
0"
#5250000000
b10 '
0&
b100 (
b10 %
b10 )
1"
#5275000000
0"
#5300000000
b11 (
0#
1"
#5325000000
0"
#5350000000
b10 (
1"
#5375000000
0"
#5400000000
b1 (
1"
#5425000000
0"
#5450000000
1&
b0 (
1"
#5475000000
0"
#5500000000
b11 '
0&
b100 (
1"
#5525000000
0"
#5550000000
b11 (
1"
#5575000000
0"
#5600000000
b10 (
1"
#5625000000
0"
#5650000000
b1 (
1"
#5675000000
0"
#5700000000
1&
b0 (
1"
#5725000000
0"
#5750000000
b100 '
0&
b100 (
1"
#5775000000
0"
#5800000000
b11 (
1"
#5825000000
0"
#5850000000
b10 (
1"
#5875000000
0"
#5900000000
b1 (
1"
#5925000000
0"
#5950000000
1&
b0 (
1"
#5975000000
0"
#6000000000
b101 '
0&
b100 (
1"
#6025000000
0"
#6050000000
b11 (
1"
#6075000000
0"
#6100000000
b10 (
1"
#6125000000
0"
#6150000000
b1 (
1"
#6175000000
0"
#6200000000
1&
b0 (
1"
#6225000000
0"
#6250000000
b110 '
0&
b100 (
1"
#6275000000
0"
#6300000000
b11 (
1"
#6325000000
0"
#6350000000
b10 (
1"
#6375000000
0"
#6400000000
b1 (
1"
#6425000000
0"
#6450000000
1&
b0 (
1"
#6475000000
0"
#6500000000
b111 '
0&
b100 (
1"
#6525000000
0"
#6550000000
b11 (
1"
#6575000000
0"
#6600000000
b10 (
1"
#6625000000
0"
#6650000000
b1 (
1"
#6675000000
0"
#6700000000
1&
b0 (
1"
#6725000000
0"
#6750000000
0+
0*
b0 '
0&
b100 (
1"
#6775000000
0"
#6800000000
1$
1+
0#
1"
#6825000000
0"
#6850000000
0$
b111 (
1*
1"
#6875000000
0"
#6900000000
b110 (
1"
#6925000000
0"
#6950000000
b101 (
1"
#6975000000
0"
#7000000000
b100 (
1"
#7025000000
0"
#7050000000
b11 (
1#
1"
#7075000000
0"
#7100000000
b10 (
1"
#7125000000
0"
#7150000000
b1 (
1"
#7175000000
0"
#7200000000
1&
b0 (
1"
#7225000000
0"
#7250000000
b1 '
0&
b100 (
b11 %
b11 )
1"
#7275000000
0"
#7300000000
b11 (
1"
#7325000000
0"
#7350000000
b10 (
1"
#7375000000
0"
#7400000000
b1 (
1"
#7425000000
0"
#7450000000
1&
b0 (
1"
#7475000000
0"
#7500000000
b10 '
0&
b100 (
1"
#7525000000
0"
#7550000000
b11 (
0#
1"
#7575000000
0"
#7600000000
b10 (
1"
#7625000000
0"
#7650000000
b1 (
1"
#7675000000
0"
#7700000000
1&
b0 (
1"
#7725000000
0"
#7750000000
b11 '
0&
b100 (
1"
#7775000000
0"
#7800000000
b11 (
1"
#7825000000
0"
#7850000000
b10 (
1"
#7875000000
0"
#7900000000
b1 (
1"
#7925000000
0"
#7950000000
1&
b0 (
1"
#7975000000
0"
#8000000000
b100 '
0&
b100 (
1"
#8025000000
0"
#8050000000
b11 (
1"
#8075000000
0"
#8100000000
b10 (
1"
#8125000000
0"
#8150000000
b1 (
1"
#8175000000
0"
#8200000000
1&
b0 (
1"
#8225000000
0"
#8250000000
b101 '
0&
b100 (
1"
#8275000000
0"
#8300000000
b11 (
1"
#8325000000
0"
#8350000000
b10 (
1"
#8375000000
0"
#8400000000
b1 (
1"
#8425000000
0"
#8450000000
1&
b0 (
1"
#8475000000
0"
#8500000000
b110 '
0&
b100 (
1"
#8525000000
0"
#8550000000
b11 (
1"
#8575000000
0"
#8600000000
b10 (
1"
#8625000000
0"
#8650000000
b1 (
1"
#8675000000
0"
#8700000000
1&
b0 (
1"
#8725000000
0"
#8750000000
b111 '
0&
b100 (
1"
#8775000000
0"
#8800000000
b11 (
1"
#8825000000
0"
#8850000000
b10 (
1"
#8875000000
0"
#8900000000
b1 (
1"
#8925000000
0"
#8950000000
1&
b0 (
1"
#8975000000
0"
#9000000000
0+
0*
b0 '
0&
b100 (
1"
#9025000000
0"
#9050000000
1$
1+
0#
1"
#9075000000
0"
#9100000000
0$
b111 (
1*
1"
#9125000000
0"
#9150000000
b110 (
1"
#9175000000
0"
#9200000000
b101 (
1"
#9225000000
0"
#9250000000
b100 (
1"
#9275000000
0"
#9300000000
b11 (
1"
#9325000000
0"
#9350000000
b10 (
1"
#9375000000
0"
#9400000000
b1 (
1"
#9425000000
0"
#9450000000
1&
b0 (
1"
#9475000000
0"
#9500000000
b1 '
0&
b100 (
b10 %
b10 )
1"
#9525000000
0"
#9550000000
b11 (
1"
#9575000000
0"
#9600000000
b10 (
1"
#9625000000
0"
#9650000000
b1 (
1"
#9675000000
0"
#9700000000
1&
b0 (
1"
#9725000000
0"
#9750000000
b10 '
0&
b100 (
b0 %
b0 )
1"
#9775000000
0"
#9800000000
b11 (
1#
1"
#9825000000
0"
#9850000000
b10 (
1"
#9875000000
0"
#9900000000
b1 (
1"
#9925000000
0"
#9950000000
1&
b0 (
1"
#9975000000
0"
#10000000000
b11 '
0&
b100 (
b100 %
b100 )
1"
#10025000000
0"
#10050000000
b11 (
0#
1"
#10075000000
0"
#10100000000
b10 (
1"
#10125000000
0"
#10150000000
b1 (
1"
#10175000000
0"
#10200000000
1&
b0 (
1"
#10225000000
0"
#10250000000
b100 '
0&
b100 (
1"
#10275000000
0"
#10300000000
b11 (
1"
#10325000000
0"
#10350000000
b10 (
1"
#10375000000
0"
#10400000000
b1 (
1"
#10425000000
0"
#10450000000
1&
b0 (
1"
#10475000000
0"
#10500000000
b101 '
0&
b100 (
1"
#10525000000
0"
#10550000000
b11 (
1"
#10575000000
0"
#10600000000
b10 (
1"
#10625000000
0"
#10650000000
b1 (
1"
#10675000000
0"
#10700000000
1&
b0 (
1"
#10725000000
0"
#10750000000
b110 '
0&
b100 (
1"
#10775000000
0"
#10800000000
b11 (
1"
#10825000000
0"
#10850000000
b10 (
1"
#10875000000
0"
#10900000000
b1 (
1"
#10925000000
0"
#10950000000
1&
b0 (
1"
#10975000000
0"
#11000000000
b111 '
0&
b100 (
1"
#11025000000
0"
#11050000000
b11 (
1"
#11075000000
0"
#11100000000
b10 (
1"
#11125000000
0"
#11150000000
b1 (
1"
#11175000000
0"
#11200000000
1&
b0 (
1"
#11225000000
0"
#11250000000
0+
0*
b0 '
0&
b100 (
1"
#11275000000
0"
#11300000000
1$
1+
0#
1"
#11325000000
0"
#11350000000
0$
b111 (
1*
1"
#11375000000
0"
#11400000000
b110 (
1"
#11425000000
0"
#11450000000
b101 (
1"
#11475000000
0"
#11500000000
b100 (
1"
#11525000000
0"
#11550000000
b11 (
1#
1"
#11575000000
0"
#11600000000
b10 (
1"
#11625000000
0"
#11650000000
b1 (
1"
#11675000000
0"
#11700000000
1&
b0 (
1"
#11725000000
0"
#11750000000
b1 '
0&
b100 (
b101 %
b101 )
1"
#11775000000
0"
#11800000000
b11 (
0#
1"
#11825000000
0"
#11850000000
b10 (
1"
#11875000000
0"
#11900000000
b1 (
1"
#11925000000
0"
#11950000000
1&
b0 (
1"
#11975000000
0"
#12000000000
b10 '
0&
b100 (
1"
#12025000000
0"
#12050000000
b11 (
1#
1"
#12075000000
0"
#12100000000
b10 (
1"
#12125000000
0"
#12150000000
b1 (
1"
#12175000000
0"
#12200000000
1&
b0 (
1"
#12225000000
0"
#12250000000
b11 '
0&
b100 (
1"
#12275000000
0"
#12300000000
b11 (
0#
1"
#12325000000
0"
#12350000000
b10 (
1"
#12375000000
0"
#12400000000
b1 (
1"
#12425000000
0"
#12450000000
1&
b0 (
1"
#12475000000
0"
#12500000000
b100 '
0&
b100 (
1"
#12525000000
0"
#12550000000
b11 (
1"
#12575000000
0"
#12600000000
b10 (
1"
#12625000000
0"
#12650000000
b1 (
1"
#12675000000
0"
#12700000000
1&
b0 (
1"
#12725000000
0"
#12750000000
b101 '
0&
b100 (
1"
#12775000000
0"
#12800000000
b11 (
1"
#12825000000
0"
#12850000000
b10 (
1"
#12875000000
0"
#12900000000
b1 (
1"
#12925000000
0"
#12950000000
1&
b0 (
1"
#12975000000
0"
#13000000000
b110 '
0&
b100 (
1"
#13025000000
0"
#13050000000
b11 (
1"
#13075000000
0"
#13100000000
b10 (
1"
#13125000000
0"
#13150000000
b1 (
1"
#13175000000
0"
#13200000000
1&
b0 (
1"
#13225000000
0"
#13250000000
b111 '
0&
b100 (
1"
#13275000000
0"
#13300000000
b11 (
1"
#13325000000
0"
#13350000000
b10 (
1"
#13375000000
0"
#13400000000
b1 (
1"
#13425000000
0"
#13450000000
1&
b0 (
1"
#13475000000
0"
#13500000000
0+
0*
b0 '
0&
b100 (
1"
#13525000000
0"
#13550000000
1$
1+
0#
1"
#13575000000
0"
#13600000000
0$
b111 (
1*
1"
#13625000000
0"
#13650000000
b110 (
1"
#13675000000
0"
#13700000000
b101 (
1"
#13725000000
0"
#13750000000
b100 (
1"
#13775000000
0"
#13800000000
b11 (
1"
#13825000000
0"
#13850000000
b10 (
1"
#13875000000
0"
#13900000000
b1 (
1"
#13925000000
0"
#13950000000
1&
b0 (
1"
#13975000000
0"
#14000000000
b1 '
0&
b100 (
b100 %
b100 )
1"
#14025000000
0"
#14050000000
b11 (
1#
1"
#14075000000
0"
#14100000000
b10 (
1"
#14125000000
0"
#14150000000
b1 (
1"
#14175000000
0"
#14200000000
1&
b0 (
1"
#14225000000
0"
#14250000000
b10 '
0&
b100 (
b110 %
b110 )
1"
#14275000000
0"
#14300000000
b11 (
1"
#14325000000
0"
#14350000000
b10 (
1"
#14375000000
0"
#14400000000
b1 (
1"
#14425000000
0"
#14450000000
1&
b0 (
1"
#14475000000
0"
#14500000000
b11 '
0&
b100 (
1"
#14525000000
0"
#14550000000
b11 (
0#
1"
#14575000000
0"
#14600000000
b10 (
1"
#14625000000
0"
#14650000000
b1 (
1"
#14675000000
0"
#14700000000
1&
b0 (
1"
#14725000000
0"
#14750000000
b100 '
0&
b100 (
1"
#14775000000
0"
#14800000000
b11 (
1"
#14825000000
0"
#14850000000
b10 (
1"
#14875000000
0"
#14900000000
b1 (
1"
#14925000000
0"
#14950000000
1&
b0 (
1"
#14975000000
0"
#15000000000
b101 '
0&
b100 (
1"
#15025000000
0"
#15050000000
b11 (
1"
#15075000000
0"
#15100000000
b10 (
1"
#15125000000
0"
#15150000000
b1 (
1"
#15175000000
0"
#15200000000
1&
b0 (
1"
#15225000000
0"
#15250000000
b110 '
0&
b100 (
1"
#15275000000
0"
#15300000000
b11 (
1"
#15325000000
0"
#15350000000
b10 (
1"
#15375000000
0"
#15400000000
b1 (
1"
#15425000000
0"
#15450000000
1&
b0 (
1"
#15475000000
0"
#15500000000
b111 '
0&
b100 (
1"
#15525000000
0"
#15550000000
b11 (
1"
#15575000000
0"
#15600000000
b10 (
1"
#15625000000
0"
#15650000000
b1 (
1"
#15675000000
0"
#15700000000
1&
b0 (
1"
#15725000000
0"
#15750000000
0+
0*
b0 '
0&
b100 (
1"
#15775000000
0"
#15800000000
1$
1+
0#
1"
#15825000000
0"
#15850000000
0$
b111 (
1*
1"
#15875000000
0"
#15900000000
b110 (
1"
#15925000000
0"
#15950000000
b101 (
1"
#15975000000
0"
#16000000000
b100 (
1"
#16025000000
0"
#16050000000
b11 (
1#
1"
#16075000000
0"
#16100000000
b10 (
1"
#16125000000
0"
#16150000000
b1 (
1"
#16175000000
0"
#16200000000
1&
b0 (
1"
#16225000000
0"
#16250000000
b1 '
0&
b100 (
b111 %
b111 )
1"
#16275000000
0"
#16300000000
b11 (
1"
#16325000000
0"
#16350000000
b10 (
1"
#16375000000
0"
#16400000000
b1 (
1"
#16425000000
0"
#16450000000
1&
b0 (
1"
#16475000000
0"
#16500000000
b10 '
0&
b100 (
1"
#16525000000
0"
#16550000000
b11 (
1"
#16575000000
0"
#16600000000
b10 (
1"
#16625000000
0"
#16650000000
b1 (
1"
#16675000000
0"
#16700000000
1&
b0 (
1"
#16725000000
0"
#16750000000
b11 '
0&
b100 (
1"
#16775000000
0"
#16800000000
b11 (
0#
1"
#16825000000
0"
#16850000000
b10 (
1"
#16875000000
0"
#16900000000
b1 (
1"
#16925000000
0"
#16950000000
1&
b0 (
1"
#16975000000
0"
#17000000000
b100 '
0&
b100 (
1"
#17025000000
0"
#17050000000
b11 (
1"
#17075000000
0"
#17100000000
b10 (
1"
#17125000000
0"
#17150000000
b1 (
1"
#17175000000
0"
#17200000000
1&
b0 (
1"
#17225000000
0"
#17250000000
b101 '
0&
b100 (
1"
#17275000000
0"
#17300000000
b11 (
1"
#17325000000
0"
#17350000000
b10 (
1"
#17375000000
0"
#17400000000
b1 (
1"
#17425000000
0"
#17450000000
1&
b0 (
1"
#17475000000
0"
#17500000000
b110 '
0&
b100 (
1"
#17525000000
0"
#17550000000
b11 (
1"
#17575000000
0"
#17600000000
b10 (
1"
#17625000000
0"
#17650000000
b1 (
1"
#17675000000
0"
#17700000000
1&
b0 (
1"
#17725000000
0"
#17750000000
b111 '
0&
b100 (
1"
#17775000000
0"
#17800000000
b11 (
1"
#17825000000
0"
#17850000000
b10 (
1"
#17875000000
0"
#17900000000
b1 (
1"
#17925000000
0"
#17950000000
1&
b0 (
1"
#17975000000
0"
#18000000000
0+
0*
b0 '
0&
b100 (
1"
#18025000000
0"
#18050000000
1$
1+
0#
1"
#18075000000
0"
#18100000000
0$
b111 (
1*
1"
#18125000000
0"
#18150000000
b110 (
1"
#18175000000
0"
#18200000000
b101 (
1"
#18225000000
0"
#18250000000
b100 (
1"
#18275000000
0"
#18300000000
b11 (
1"
#18325000000
0"
#18350000000
b10 (
1"
#18375000000
0"
#18400000000
b1 (
1"
#18425000000
0"
#18450000000
1&
b0 (
1"
#18475000000
0"
#18500000000
b1 '
0&
b100 (
b110 %
b110 )
1"
#18525000000
0"
#18550000000
b11 (
1"
#18575000000
0"
#18600000000
b10 (
1"
#18625000000
0"
#18650000000
b1 (
1"
#18675000000
0"
#18700000000
1&
b0 (
1"
#18725000000
0"
#18750000000
b10 '
0&
b100 (
b100 %
b100 )
1"
#18775000000
0"
#18800000000
b11 (
1"
#18825000000
0"
#18850000000
b10 (
1"
#18875000000
0"
#18900000000
b1 (
1"
#18925000000
0"
#18950000000
1&
b0 (
1"
#18975000000
0"
#19000000000
b11 '
0&
b100 (
b0 %
b0 )
1"
#19025000000
0"
#19050000000
b11 (
1#
1"
#19075000000
0"
#19100000000
b10 (
1"
#19125000000
0"
#19150000000
b1 (
1"
#19175000000
0"
#19200000000
1&
b0 (
1"
#19225000000
0"
#19250000000
b100 '
0&
b100 (
b1000 %
b1000 )
1"
#19275000000
0"
#19300000000
b11 (
0#
1"
#19325000000
0"
#19350000000
b10 (
1"
#19375000000
0"
#19400000000
b1 (
1"
#19425000000
0"
#19450000000
1&
b0 (
1"
#19475000000
0"
#19500000000
b101 '
0&
b100 (
1"
#19525000000
0"
#19550000000
b11 (
1"
#19575000000
0"
#19600000000
b10 (
1"
#19625000000
0"
#19650000000
b1 (
1"
#19675000000
0"
#19700000000
1&
b0 (
1"
#19725000000
0"
#19750000000
b110 '
0&
b100 (
1"
#19775000000
0"
#19800000000
b11 (
1"
#19825000000
0"
#19850000000
b10 (
1"
#19875000000
0"
#19900000000
b1 (
1"
#19925000000
0"
#19950000000
1&
b0 (
1"
#19975000000
0"
#20000000000
b111 '
0&
b100 (
1"
#20025000000
0"
#20050000000
b11 (
1"
#20075000000
0"
#20100000000
b10 (
1"
#20125000000
0"
#20150000000
b1 (
1"
#20175000000
0"
#20200000000
1&
b0 (
1"
#20225000000
0"
#20250000000
0+
0*
b0 '
0&
b100 (
1"
#20275000000
0"
#20300000000
1$
1+
0#
1"
#20325000000
0"
#20350000000
0$
b111 (
1*
1"
#20375000000
0"
#20400000000
b110 (
1"
#20425000000
0"
#20450000000
b101 (
1"
#20475000000
0"
#20500000000
b100 (
1"
#20525000000
0"
#20550000000
b11 (
1#
1"
#20575000000
0"
#20600000000
b10 (
1"
#20625000000
0"
#20650000000
b1 (
1"
#20675000000
0"
#20700000000
1&
b0 (
1"
#20725000000
0"
#20750000000
b1 '
0&
b100 (
b1001 %
b1001 )
1"
#20775000000
0"
#20800000000
b11 (
0#
1"
#20825000000
0"
#20850000000
b10 (
1"
#20875000000
0"
#20900000000
b1 (
1"
#20925000000
0"
#20950000000
1&
b0 (
1"
#20975000000
0"
#21000000000
b10 '
0&
b100 (
1"
#21025000000
0"
#21050000000
b11 (
1"
#21075000000
0"
#21100000000
b10 (
1"
#21125000000
0"
#21150000000
b1 (
1"
#21175000000
0"
#21200000000
1&
b0 (
1"
#21225000000
0"
#21250000000
b11 '
0&
b100 (
1"
#21275000000
0"
#21300000000
b11 (
1#
1"
#21325000000
0"
#21350000000
b10 (
1"
#21375000000
0"
#21400000000
b1 (
1"
#21425000000
0"
#21450000000
1&
b0 (
1"
#21475000000
0"
#21500000000
b100 '
0&
b100 (
1"
#21525000000
0"
#21550000000
b11 (
0#
1"
#21575000000
0"
#21600000000
b10 (
1"
#21625000000
0"
#21650000000
b1 (
1"
#21675000000
0"
#21700000000
1&
b0 (
1"
#21725000000
0"
#21750000000
b101 '
0&
b100 (
1"
#21775000000
0"
#21800000000
b11 (
1"
#21825000000
0"
#21850000000
b10 (
1"
#21875000000
0"
#21900000000
b1 (
1"
#21925000000
0"
#21950000000
1&
b0 (
1"
#21975000000
0"
#22000000000
b110 '
0&
b100 (
1"
#22025000000
0"
#22050000000
b11 (
1"
#22075000000
0"
#22100000000
b10 (
1"
#22125000000
0"
#22150000000
b1 (
1"
#22175000000
0"
#22200000000
1&
b0 (
1"
#22225000000
0"
#22250000000
b111 '
0&
b100 (
1"
#22275000000
0"
#22300000000
b11 (
1"
#22325000000
0"
#22350000000
b10 (
1"
#22375000000
0"
#22400000000
b1 (
1"
#22425000000
0"
#22450000000
1&
b0 (
1"
#22475000000
0"
#22500000000
0+
0*
b0 '
0&
b100 (
1"
#22525000000
0"
#22550000000
1$
1+
0#
1"
#22575000000
0"
#22600000000
0$
b111 (
1*
1"
#22625000000
0"
#22650000000
b110 (
1"
#22675000000
0"
#22700000000
b101 (
1"
#22725000000
0"
#22750000000
b100 (
1"
#22775000000
0"
#22800000000
b11 (
1"
#22825000000
0"
#22850000000
b10 (
1"
#22875000000
0"
#22900000000
b1 (
1"
#22925000000
0"
#22950000000
1&
b0 (
1"
#22975000000
0"
#23000000000
b1 '
0&
b100 (
b1000 %
b1000 )
1"
#23025000000
0"
#23050000000
b11 (
1#
1"
#23075000000
0"
#23100000000
b10 (
1"
#23125000000
0"
#23150000000
b1 (
1"
#23175000000
0"
#23200000000
1&
b0 (
1"
#23225000000
0"
#23250000000
b10 '
0&
b100 (
b1010 %
b1010 )
1"
#23275000000
0"
#23300000000
b11 (
0#
1"
#23325000000
0"
#23350000000
b10 (
1"
#23375000000
0"
#23400000000
b1 (
1"
#23425000000
0"
#23450000000
1&
b0 (
1"
#23475000000
0"
#23500000000
b11 '
0&
b100 (
1"
#23525000000
0"
#23550000000
b11 (
1#
1"
#23575000000
0"
#23600000000
b10 (
1"
#23625000000
0"
#23650000000
b1 (
1"
#23675000000
0"
#23700000000
1&
b0 (
1"
#23725000000
0"
#23750000000
b100 '
0&
b100 (
1"
#23775000000
0"
#23800000000
b11 (
0#
1"
#23825000000
0"
#23850000000
b10 (
1"
#23875000000
0"
#23900000000
b1 (
1"
#23925000000
0"
#23950000000
1&
b0 (
1"
#23975000000
0"
#24000000000
b101 '
0&
b100 (
1"
#24025000000
0"
#24050000000
b11 (
1"
#24075000000
0"
#24100000000
b10 (
1"
#24125000000
0"
#24150000000
b1 (
1"
#24175000000
0"
#24200000000
1&
b0 (
1"
#24225000000
0"
#24250000000
b110 '
0&
b100 (
1"
#24275000000
0"
#24300000000
b11 (
1"
#24325000000
0"
#24350000000
b10 (
1"
#24375000000
0"
#24400000000
b1 (
1"
#24425000000
0"
#24450000000
1&
b0 (
1"
#24475000000
0"
#24500000000
b111 '
0&
b100 (
1"
#24525000000
0"
#24550000000
b11 (
1"
#24575000000
0"
#24600000000
b10 (
1"
#24625000000
0"
#24650000000
b1 (
1"
#24675000000
0"
#24700000000
1&
b0 (
1"
#24725000000
0"
#24750000000
0+
0*
b0 '
0&
b100 (
1"
#24775000000
0"
#24800000000
1$
1+
0#
1"
#24825000000
0"
#24850000000
0$
b111 (
1*
1"
#24875000000
0"
#24900000000
b110 (
1"
#24925000000
0"
#24950000000
b101 (
1"
#24975000000
0"
#25000000000
b100 (
1"
#25025000000
0"
